serial_monitor/__init__.py
serial_monitor/__main__.py
serial_monitor/k6gte-serial_monitor-32.png
serial_monitor/k6gte-serial_monitor-64.png
serial_monitor/k6gte-serial_monitor.desktop
serial_monitor/usb_plug_connected.png
serial_monitor/usb_plug_disconnected.png
serial_monitor-1.2.0.dist-info/LICENSE
serial_monitor-1.2.0.dist-info/METADATA
serial_monitor-1.2.0.dist-info/WHEEL
serial_monitor-1.2.0.dist-info/entry_points.txt
serial_monitor-1.2.0.dist-info/top_level.txt
serial_monitor-1.2.0.dist-info/RECORD
