Metadata-Version: 2.1
Name: serial-monitor
Version: 1.2.0
Summary: Notifications of adding/removing serial ports.
Author-email: Michael Bridak <michael.bridak@gmail.com>
Project-URL: Homepage, https://github.com/mbridak/serial_monitor
Project-URL: Bug Tracker, https://github.com/mbridak/serial_monitor/issues
Classifier: Programming Language :: Python :: 3
Classifier: Development Status :: 5 - Production/Stable
Classifier: License :: OSI Approved :: MIT License
Classifier: Environment :: X11 Applications :: Gnome
Classifier: Operating System :: POSIX :: Linux
Classifier: Intended Audience :: End Users/Desktop
Classifier: Natural Language :: English
Classifier: Topic :: System :: Monitoring
Requires-Python: >=3.9
License-File: LICENSE
Requires-Dist: pySerial
Requires-Dist: psutil
